bluospy/__init__.py
bluospy/data.py
bluospy/player.py
bluospy/queries.py
bluospy/utils.py
bluospy-0.1.0.dist-info/METADATA
bluospy-0.1.0.dist-info/WHEEL
bluospy-0.1.0.dist-info/licenses/LICENSE
bluospy-0.1.0.dist-info/RECORD
