Metadata-Version: 2.3
Name: bluospy
Version: 0.1.0
Summary: A Python library for controlling BlueOS players via REST API
Project-URL: Homepage, https://github.com/ohm314/bluospy
Project-URL: Repository, https://github.com/ohm314/bluospy
Author-email: Omar Awile <omar@awile.net>
License:                                  Apache License
License-File: LICENSE
Keywords: REST,bluos,music,player,streaming
Classifier: Development Status :: 3 - Alpha
Classifier: Intended Audience :: Developers
Classifier: License :: OSI Approved :: Apache Software License
Classifier: Operating System :: OS Independent
Classifier: Programming Language :: Python :: 3
Classifier: Programming Language :: Python :: 3.8
Classifier: Programming Language :: Python :: 3.9
Classifier: Programming Language :: Python :: 3.10
Classifier: Programming Language :: Python :: 3.11
Classifier: Programming Language :: Python :: 3.12
Classifier: Topic :: Multimedia :: Sound/Audio :: Players
Requires-Python: >=3.8
Requires-Dist: requests
